hello.py
hello_from_shiphero/__init__.py
hello_from_shiphero-0.0.1.dist-info/METADATA
hello_from_shiphero-0.0.1.dist-info/WHEEL
hello_from_shiphero-0.0.1.dist-info/top_level.txt
hello_from_shiphero-0.0.1.dist-info/RECORD
