Metadata-Version: 2.4
Name: hello-from-shiphero
Version: 0.0.1
Summary: PoC for dependency confusion by Ousski
Author: Ousski
Author-email: ousskr@gmail.com
Classifier: Programming Language :: Python :: 3
Classifier: License :: OSI Approved :: MIT License
Requires-Python: >=3.6
Dynamic: author
Dynamic: author-email
Dynamic: classifier
Dynamic: description
Dynamic: description-content-type
Dynamic: requires-python
Dynamic: summary
